{
  "movie_id": "tt0092099",
  "title": "Top Gun",
  "year": "1986",
  "director": "Tony Scott",
  "genre": "Action, Drama",
  "rated": "PG",
  "actors": [
    "Tom Cruise",
    "Tim Robbins",
    "Kelly McGillis"
  ],
  "plot": "The Top Gun Naval Fighter Weapons School is where the best of the best train to refine their elite flying skills. When hotshot fighter pilot Maverick is sent to the school, his reckless attitude and cocky demeanor put him at odds ...",
  "runtime": "110 min",
  "critic_score": "59%",
  "imdb_rating": "7.0",
  "poster_url": "https://m.media-amazon.com/images/M/MV5BZmVjNzQ3MjYtYTZiNC00Y2YzLWExZTEtMTM2ZDllNDI0MzgyXkEyXkFqcGc@._V1_SX300.jpg"
}