[{"name":"All About Hits","songs":["01. Alex Warren - Ordinary","02. Teddy Swims - Bad Dreams","03. Rose - APT","04. Benson Boone - Sorry I\u0027m Here for Someone Else","05. Lizzo - Still Bad","06. Charli XCX - Apple","07. David Guetta - Forever Young","08. Jisoo - earthquake","09. Jack Harlow - Just Us (feat. Doja Cat)","10. Sam Barber - Indigo (feat. Avery Anna)","11. Coldplay - WE PRAY (feat. Little Simz, Burna Boy, Elyanna \u0026 TINI)","12. Zach Bryan - Blue Jean Baby","13. Don Toliver - No Pole","14. Ava Max - Lost Your Faith","15. Ravyn Lenae - Love Me Not","16. Cameron Whitcomb - Medusa","17. Burna Boy - Update","18. Nessa Barrett - PORNSTAR","19. Sexyy Red - Fat Juicy \u0026 Wet","20. Rachel Chinouriri - All I Ever Asked","21. Linkin Park - The Emptiness Machine","22. Michael Marcagi - Flyover State","23. Don Toliver - LV Bag (feat. j-hope of BTS \u0026 Pharrell Williams)","24. Dasha - Not at This Party","25. David Guetta - Beautiful People","26. The Black Keys - The Night Before","27. Ti\u00EBsto - I Follow Rivers (feat. Oaks)","28. Teddy Swims - Are You Even Real (feat. Giv\u0113on)","29. Chloe Moriondo - shoreline","30. W Sound - La Plena","31. Knox - Pick Your Poison","32. Coldplay - ALL MY LOVE","33. Avery Anna - Mr. Predictable","34. Benson Boone - Beautiful Things","35. Danny Ocean - Imag\u00EDnate","36. Alex Sampson - Used to You","37. Alex Warren - Burning Down (with Joe Jonas)","38. Bella Poarch - Will You Always Love Her","39. Daniel Seavey - Gateway Drug","40. Rose - toxic till the end","41. Forest Blakk - Love You \u0027Til Death","42. Sofia Reyes - Guaro con ron","43. Cameron Whitcomb - Options","44. Jenna Raine - 21","45. Teddy Swims - Guilty","46. Griff - last night\u0027s mascara","47. Rainbow Kitten Surprise - Espionage","48. Charli XCX - B2b","49. Nessa Barrett - LOVE LOOKS PRETTY ON YOU","50. Leigh-Anne - Nature","51. Josh Groban - Be Alright","52. Anne-Marie - Don\u0027t Panic"],"checked":[[0,0,0,0,0,0,0,0,0,0,0,0,0,0,0,0,0,0,0,0,0,0,0,0,0,0,0,0,0,0,0,0,0,0,0,0,0,0,0,0,0,0,0,0,0,0,0,0,0,0,0,0],[0,0,0,0,0,0,0,0,0,0,0,0,0,0,0,0,0,0,0,0,0,0,0,0,0,0,0,0,0,0,0,0,0,0,0,0,0,0,0,0,0,0,0,0,0,0,0,0,0,0,0,0],[0,0,0,0,0,0,0,0,0,0,0,0,0,0,0,0,0,0,0,0,0,0,0,0,0,0,0,0,0,0,0,0,0,0,0,0,0,0,0,0,0,0,0,0,0,0,0,0,0,0,0,0],[0,0,0,0,0,0,0,0,0,0,0,0,0,0,0,0,0,0,0,0,0,0,0,0,0,0,0,0,0,0,0,0,0,0,0,0,0,0,0,0,0,0,0,0,0,0,0,0,0,0,0,0],[0,0,0,0,0,0,0,0,0,0,0,0,0,0,0,0,0,0,0,0,0,0,0,0,0,0,0,0,0,0,0,0,0,0,0,0,0,0,0,0,0,0,0,0,0,0,0,0,0,0,0,0]]},{"name":"Classic Rock","songs":["01. Led Zeppelin - Whole Lotta Love","02. The Rolling Stones - Start Me Up (Remastered)","03. Jimi Hendrix - Purple Haze","04. Queen - Bohemian Rhapsody","05. The Who - Baba O\u0027Riley","06. Pink Floyd - Comfortably Numb","07. AC_DC - You Shook Me All Night Long","08. Eagles - Hotel California","09. Aerosmith - Sweet Emotion","10. The Beatles - Hey Jude (Remastered 2009)","11. Derek \u0026 The Dominos - Layla","12. Lynyrd Skynyrd - Sweet Home Alabama","13. Creedence Clearwater Revival - Bad Moon Rising","14. Deep Purple - Smoke on the Water","15. Journey - Don\u0027t Stop Believin\u0027","16. Bob Seger \u0026 The Silver Bullet Band - Old Time Rock \u0026 Roll","17. ZZ Top - Legs","18. The Doors - Roadhouse Blues","19. Neil Young - Cinnamon Girl","20. Thin Lizzy - The Boys Are Back In Town","21. The Sounds Of Led Zeppelin - Stairway To Heaven","22. Rush - Tom Sawyer","23. The Rolling Stones - Sympathy For The Devil","24. Bruce Springsteen - Born in the U.S.A","25. Jimi Hendrix - All Along the Watchtower","26. Heart - Barracuda","27. Queen - Under Pressure (Remastered 2011 _ New Master)","28. The Allman Brothers Band - Ramblin\u0027 Man","29. The Who - Pinball Wizard","30. Boston - More Than a Feeling","31. Pink Floyd - Wish You Were Here","32. Bad Company - Feel Like Makin\u0027 Love","33. AC_DC - Back In Black","34. Fleetwood Mac - The Chain (2004 Remaster)","35. Eagles - Take It Easy","36. Tom Petty and the Heartbreakers - American Girl","37. Aerosmith - Dream On","38. Elton John - Tiny Dancer","39. The Beatles - Come Together (2019 Mix)","40. Steve Miller Band - The Joker (Remastered 2017)","41. Van Halen - You Really Got Me (2015 Remaster)","42. Foreigner - Juke Box Hero","43. Cream - Sunshine Of Your Love","44. Lynyrd Skynyrd - Free Bird","45. Creedence Clearwater Revival - Fortunate Son","46. Journey - Separate Ways (Worlds Apart)","47. Bob Seger \u0026 The Silver Bullet Band - Night Moves","48. ZZ Top - La Grange","49. The Doors - Light My Fire","50. Neil Young - Heart of Gold","51. In The Light of Led Zeppelin - Ramble On","52. Rush - Limelight","53. The Rolling Stones - Honky Tonk Women","54. Bruce Springsteen - Born to Run","55. Black Sabbath - Paranoid","56. Jimi Hendrix - Voodoo Child (Slight Return)","57. Heart - Crazy On You","58. David Bowie - Space Oddity","59. Santana - Black Magic Woman (Single Version)","60. The Allman Brothers Band - Melissa","61. The Who - Won\u0027t Get Fooled Again (Original Album Version)","62. Alice Cooper - No More Mr. Nice Guy","63. Styx - Come Sail Away","64. Pink Floyd - Another Brick in the Wall, Pt. 2","65. Free - All Right Now","66. AC_DC - Dirty Deeds Done Dirt Cheap","67. Janis Joplin - Me and Bobby McGee","68. Fleetwood Mac - Go Your Own Way (2004 Remaster)","69. Eagles - Life In The Fast Lane (Live On MTV, 1994)","70. Tom Petty - I Won\u0027t Back Down","71. Steppenwolf - Born To Be Wild","72. Aerosmith - Walk This Way","73. Elton John - Bennie And The Jets (Remastered 2014)","74. The Beatles - Here Comes The Sun","75. The Doobie Brothers - Listen to the Music","76. Steve Miller Band - Rock\u0027n Me","77. Van Halen - Runnin\u0027 with the Devil","78. Foreigner - Hot Blooded","79. Jethro Tull - Locomotive Breath","80. Eric Clapton - Cocaine","81. Lynyrd Skynyrd - Simple Man","82. Creedence Clearwater Revival - Down On The Corner","83. Journey - Any Way You Want It","84. Bob Seger - Turn The Page","85. ZZ Top - Tush","86. The Doors - Riders on the Storm","87. Neil Young - Down by the River","88. In The Light of Led Zeppelin - Kashmir","89. Rush - Closer To The Heart","90. The Rolling Stones - (I Can\u0027t Get No) Satisfaction","91. Bruce Springsteen - Thunder Road","92. Jimi Hendrix - Hey Joe","93. Queen - Another One Bites The Dust (2011 Remaster)","94. The Allman Brothers Band - Midnight Rider","95. The Who - I Can See For Miles (Mono Version)","96. Mountain - Mississippi Queen","97. Pink Floyd - Money","98. Bad Company - Can\u0027t Get Enough","99. Tom Petty and the Heartbreakers - Refugee"],"checked":[[1,1,1,1,1,1,1,1,1,1,1,1,1,1,1,1,1,1,1,1,1,1,1,1,1,1,1,1,1,1,1,1,1,1,1,1,1,1,1,1,1,1,1,1,1,1,1,1,1,1,1,1,1,1,1,1,1,1,1,1,1,1,1,1,1,1,1,1,1,1,1,1,1,1,1,1,1,1,1,1,1,1,1,1,1,1,1,1,1,1,1,1,1,1,1,1,1,1,1],[0,0,0,0,0,0,0,0,0,0,0,0,0,0,0,0,0,0,0,0,0,0,0,0,0,0,0,0,0,0,0,0,0,0,0,0,0,0,0,0,0,0,0,0,0,0,0,0,0,0,0,0,0,0,0,0,0,0,0,0,0,0,0,0,0,0,0,0,0,0,0,0,0,0,0,0,0,0,0,0,0,0,0,0,0,0,0,0,0,0,0,0,0,0,0,0,0,0,0],[0,0,0,0,0,0,0,0,0,0,0,0,0,0,0,0,0,0,0,0,0,0,0,0,0,0,0,0,0,0,0,0,0,0,0,0,0,0,0,0,0,0,0,0,0,0,0,0,0,0,0,0,0,0,0,0,0,0,0,0,0,0,0,0,0,0,0,0,0,0,0,0,0,0,0,0,0,0,0,0,0,0,0,0,0,0,0,0,0,0,0,0,0,0,0,0,0,0,0],[0,0,0,0,0,0,0,0,0,0,0,0,0,0,0,0,0,0,0,0,0,0,0,0,0,0,0,0,0,0,0,0,0,0,0,0,0,0,0,0,0,0,0,0,0,0,0,0,0,0,0,0,0,0,0,0,0,0,0,0,0,0,0,0,0,0,0,0,0,0,0,0,0,0,0,0,0,0,0,0,0,0,0,0,0,0,0,0,0,0,0,0,0,0,0,0,0,0,0],[0,0,0,0,0,0,0,0,0,0,0,0,0,0,0,0,0,0,0,0,0,0,0,0,0,0,0,0,0,0,0,0,0,0,0,0,0,0,0,0,0,0,0,0,0,0,0,0,0,0,0,0,0,0,0,0,0,0,0,0,0,0,0,0,0,0,0,0,0,0,0,0,0,0,0,0,0,0,0,0,0,0,0,0,0,0,0,0,0,0,0,0,0,0,0,0,0,0,0]]},{"name":"Classical","songs":["01. Siegbert Rampe - Brandenburgische Konzert No. 3 in G Major, BWV 1048 I. [Tempo d\u0027allabreve]","02. Claudio Abbado - Clarinet Concerto in A Major, K. 622 III. Rondo. Allegro","03. Sir Simon Rattle - The Nutcracker, Op. 71, Act I No. 2, March","04. Mariss Jansons - Suite for Jazz Orchestra No. 1 II. Polka","05. David Charles Abell - West Side Story, Act II I Feel Pretty","06. Hans Vonk - Piano concerto No. 1 in C Major, Op. 15 III. Rondo - Allegro scherzando (Cadenza by Zacharias)","07. Fabio Biondi - Mandolin Concerto in C Major, RV 425 I. Allegro","08. Sir Neville Marriner - Canon and Gigue in D Major, P. 37 I. Canon","09. Sir Simon Rattle - Symphony No. 7 in A Major, Op. 92 III. Presto - Assai meno presto","10. Sir Simon Rattle - Bol\u00E9ro, M. 81","11. Andr\u00E9 Previn - Swan Lake, Op. 20, Act II No. 13, Dances of the Swans. Tempo di valse","12. Mariss Jansons - Petrushka, K 012, Pt. 1 Le tour dr passe-passe - Danse russe","13. Zubin Mehta - La traviata, Act I Libiamo ne\u0027 lieti calici (Alfredo, Violetta, Chorus)","14. Jeffrey Tate - Symphony No. 42 in F Major, K. 75 I. Allegro","15. Mariss Jansons - Suite for Jazz Orchestra No. 1 I. Waltz in G Minor","16. Bernard Labadie - Piano Concerto No. 9 in E-Flat Major, K. 271 Jeunehomme III. Rondo. Presto","17. Peter Donohoe - George Gershwin\u0027s Song-Book VII. Liza (All the clouds\u0027ll roll away)","18. Mariss Jansons - Suite for Jazz Orchestra No. 1 III. Foxtrot in F-Sharp Minor","19. Mariss Jansons - Suite for Variety Orchestra VII. Waltz 2","20. Andr\u00E9 Previn - Swan Lake, Op. 20, Act III 21. Spanish Dance. Allegro non troppo - Tempo di bolero","21. Sir Simon Rattle - The Nutcracker, Op. 71, Act II No. 12b, Divertissement. Coffee (Arab Dance)","22. James Levine - Il Barbiere di Siviglia Overture","23. Mariss Jansons - Tahiti Trot, Op. 16","24. Sir Neville Marriner - Toy Symphony I. Allegro","25. Daniel Barenboim - Le Nozze di Figaro, K. 492 Overture","26. Andr\u00E9 Previn - Swan Lake, Op. 20, Act II No. 13d, Danses des cygnes. Allegro moderato","27. Sir Simon Rattle - The Nutcracker, Op. 71a I. Miniature Overture. Allegro giusto","28. Michel Plasson - Carmina Burana V. Ecce Gratum","29. Franck Braley - Hungarian Dances, WoO. 1 No. 3 in F Major. Allegretto","30. John Nelson - L\u0027Allegro, il Penseroso ed il Moderato, HWV 55, Act I Air \u0026 Chorus. Haste thee, nymph","31. Jeffrey Tate - Symphony No. 40 in G Minor, K. 550 I. Molto allegro","32. Sir Simon Rattle - The Nutcracker, Op. 71, Act II No. 12c, Divertissement. Tea (Chinese Dance)","33. Sir Simon Rattle - Porgy and Bess, Act II Mus\u0027 be you mens forgot about de picnic...Oh, I got plenty o\u0027 nuttin\u0027","34. Sir Neville Marriner - Toy Symphony III. Allegro moderato","35. Sir Neville Marriner - Peer Gynt, Op. 23, Act IV Anitra\u0027s Dance","36. Andr\u00E9 Previn - Swan Lake, Op. 20, Act IV No. 27, Dance of the Little Swans. Moderato","37. Sir Neville Marriner - Peer Gynt, Op. 23, Act II No. 8, In the Hall of the Mountain King","38. Claudio Abbado - Flute Concerto No. 1 in G Major, K. 313 III. Rondo. Tempo di menuetto","39. Wayne Marshall - Girl Crazy, Act I I Got Rhythm","40. Willi Boskovsky - Fr\u00FChlingstimmen, Op. 410","41. Andr\u00E9 Previn - Wedding Cake in A-Flat Major, Op. 76","42. David Charles Abell - Die Fledermaus, Act II Mein Herr, Marquis","43. David Charles Abell - Snow White and the Seven Dwarfs No. 6, Some Day My Prince Will Come","44. Nigel Kennedy - The Four Seasons, Violin Concerto No. 1 in E Major, RV 269 Spring III. Danza pastorala. Allegro","45. Jean-Christophe Spinosi - Demofoonte, RV deest Sperai vicino il lido","46. Georges Pr\u00EAtre - La Damnation de Faust, H. 111, Pt. 1 No. 3, Marche hongroise","47. Franck Braley - Hungarian Dances, WoO. 1 No. 5 in F-Sharp Minor. Allegro","48. Michel Plasson - Faust, CG 4, Act III Un bouquet !... O Dieu ! que de bijoux ! (Marguerite)","49. Willi Boskovsky - Les Patineurs, Op. 183","50. Willi Boskovsky - Invitation to the Dance, Op. 65","51. Fabio Biondi - Violin Concerto in F Major, RV 293 L\u0027autunno III. Allegro","52. Mariss Jansons - Die Walk\u00FCre, WWV 86B, Act III Ride of the Valkyries (Concert Version)"],"checked":[[0,0,0,0,0,0,0,0,0,0,0,0,0,0,0,0,0,0,0,0,0,0,0,0,0,0,0,0,0,0,0,0,0,0,0,0,0,0,0,0,0,0,0,0,0,0,0,0,0,0,0,0],[1,1,1,1,1,1,1,1,1,1,1,1,1,1,1,1,1,1,1,1,1,1,1,1,1,1,1,1,1,1,1,1,1,1,1,1,1,1,1,1,1,1,1,1,1,1,1,1,1,1,1,1],[0,0,0,0,0,0,0,0,0,0,0,0,0,0,0,0,0,0,0,0,0,0,0,0,0,0,0,0,0,0,0,0,0,0,0,0,0,0,0,0,0,0,0,0,0,0,0,0,0,0,0,0],[0,0,0,0,0,0,0,0,0,0,0,0,0,0,0,0,0,0,0,0,0,0,0,0,0,0,0,0,0,0,0,0,0,0,0,0,0,0,0,0,0,0,0,0,0,0,0,0,0,0,0,0],[1,1,1,1,1,1,1,1,1,1,1,1,1,1,1,1,1,1,1,1,1,1,1,1,1,1,1,1,1,1,1,1,1,1,1,1,1,1,1,1,1,1,1,1,1,1,1,1,1,1,1,1]]},{"name":"Country Vibes","songs":["01. Kid Rock - All Summer Long","02. Bebe Rexha - Meant to Be (feat. Florida Georgia Line)","03. Kenny Chesney - Get Along","04. Blake Shelton - Honey Bee","05. Cole Swindell - Chillin\u2019 It","06. Randall King - You in a Honky Tonk","07. Michael Ray - Whiskey and Rain","08. Bailey Zimmerman - Rock and a Hard Place","09. Zach Bryan - Heading South","10. Brett Eldredge - Lose My Mind","11. Dasha - Austin","12. Redferrin - Jack and Diet Coke","13. James Otto - Just Got Started Lovin\u2019 You","14. Michael Marcagi - Scared to Start","15. Chris Janson - Fix a Drink","16. Brett Eldredge - Songs About You","17. Cody Johnson - \u2019Til You Can\u2019t","18. Dan \u002B Shay - Tequila","19. Bailey Zimmerman - Fall in Love","20. Kenny Chesney - Happy Does","21. Ian Munsick - Long Live Cowgirls","22. Zach Bryan - I Remember Everything (feat. Kacey Musgraves)","23. Cole Swindell - She Had Me at Heads Carolina","24. Blake Shelton - God\u2019s Country","25. Morgan Evans - Day Drunk","26. Breland - Praise the Lord (feat. Thomas Rhett)","27. Redferrin - Miss Summer","28. Dan \u002B Shay - All Nighter","29. Dasha - Not at This Party","30. Bailey Zimmerman - Holy Smokes"],"checked":[[0,0,0,0,0,0,0,0,0,0,0,0,0,0,0,0,0,0,0,0,0,0,0,0,0,0,0,0,0,0],[0,0,0,0,0,0,0,0,0,0,0,0,0,0,0,0,0,0,0,0,0,0,0,0,0,0,0,0,0,0],[0,0,0,0,0,0,0,0,0,0,0,0,0,0,0,0,0,0,0,0,0,0,0,0,0,0,0,0,0,0],[0,0,0,0,0,0,0,0,0,0,0,0,0,0,0,0,0,0,0,0,0,0,0,0,0,0,0,0,0,0],[0,0,0,0,0,0,0,0,0,0,0,0,0,0,0,0,0,0,0,0,0,0,0,0,0,0,0,0,0,0]]},{"name":"Jimi Hendrix","songs":["01. All Along the Watchtower","02. Purple Haze","03. Voodoo Child (Slight Return)","04. Hey Joe","05. Fire","06. Little Wing","07. Foxey Lady","08. Crosstown Traffic","09. The Wind Cries Mary","10. Castles Made of Sand","11. Red House","12. (Have You Ever Been To) Electric Ladyland (Record Plant, New York, NY, June 14, 1968)","13. Burning of the Midnight Lamp","14. Angel","15. Spanish Castle Magic","16. If 6 Was 9","17. Freedom","18. Wait Until Tomorrow","19. Stone Free","20. Bold as Love","21. Are You Experienced","22. Bleeding Heart","23. Manic Depression","24. Star Spangled Banner (Live)","25. Machine Gun (Live)"],"checked":[[1,1,1,1,1,1,1,1,1,1,1,1,1,1,1,1,1,1,1,1,1,1,1,1,1],[0,0,0,0,0,0,0,0,0,0,0,0,0,0,0,0,0,0,0,0,0,0,0,0,0],[0,0,0,0,0,0,0,0,0,0,0,0,0,0,0,0,0,0,0,0,0,0,0,0,0],[1,1,1,1,1,1,1,1,1,1,1,1,1,1,1,1,1,1,1,1,1,1,1,1,1],[0,0,0,0,0,0,0,0,0,0,0,0,0,0,0,0,0,0,0,0,0,0,0,0,0]]},{"name":"Led Zeppelin","songs":["01. Whole Lotta Love","02. Stairway To Heaven","03. Living Loving Maid (She\u0027s Just A Woman)","04. Since I\u0027ve Been Loving You","05. Immigrant Song","06. D\u0027Yer Mak\u0027er","07. Communication Breakdown","08. All My Love","09. Hots On For Nowhere","10. Black Dog","11. Good Times Bad Times","12. Thank You","13. Over The Hills And Far Away","14. Hot Dog","15. Out on the Tiles","16. The Song Remains The Same","17. Ramble On","18. When The Levee Breaks","19. Bron-Y-Aur Stomp","20. Kashmir","21. Rock And Roll","22. Babe I\u0027m Gonna Leave You","23. You Shook Me","24. Dazed And Confused","25. Heartbreaker","26. Gallows Pole","27. Boogie With Stu","28. What Is And What Should Never Be","29. Bring It On Home","30. Poor Tom","31. South Bound Saurez"],"checked":[[0,0,0,0,0,0,0,0,0,0,0,0,0,0,0,0,0,0,0,0,0,0,0,0,0,0,0,0,0,0,0],[0,0,0,0,0,0,0,0,0,0,0,0,0,0,0,0,0,0,0,0,0,0,0,0,0,0,0,0,0,0,0],[0,0,0,0,0,0,0,0,0,0,0,0,0,0,0,0,0,0,0,0,0,0,0,0,0,0,0,0,0,0,0],[0,0,0,0,0,0,0,0,0,0,0,0,0,0,0,0,0,0,0,0,0,0,0,0,0,0,0,0,0,0,0],[0,0,0,0,0,0,0,0,0,0,0,0,0,0,0,0,0,0,0,0,0,0,0,0,0,0,0,0,0,0,0]]},{"name":"Moog Cookbook","songs":["01. Black Hole Sun","02. Buddy Holly","03. Basket Case","04. Come Out and Play","05. Free Fallin\u0027","06. Are You Gonna Go My Way\uFF1F","07. Smells Like Teen Spirit","08. Evenflow","09. The One I Love","10. Rockin\u0027 In the Free World","11. Born to Be Wild","12. Cat Scratch Fever","13. Sweet Home Alabama","14. More Than a Feeling","15. Ain\u0027t Talkin\u0027 \u0027bout Love","16. Whole Lotta Love","17. Ziggy Stardust","18. 25 or 6 to 4","19. Hotel California","20. Rock and Roll All Night"],"checked":[[0,0,0,0,0,0,0,0,0,0,0,0,0,0,0,0,0,0,0,0],[0,0,0,0,0,0,0,0,0,0,0,0,0,0,0,0,0,0,0,0],[1,1,1,1,1,1,1,1,1,1,1,1,1,1,1,1,1,1,1,1],[0,0,0,0,0,0,0,0,0,0,0,0,0,0,0,0,0,0,0,0],[0,0,0,0,0,0,0,0,0,0,0,0,0,0,0,0,0,0,0,0]]},{"name":"1970s","songs":["01. Christopher Cross - Ride like the Wind","02. Kate Bush - Wuthering Heights","03. Fleetwood Mac - Go Your Own Way (2018 Remaster)","04. War - Low Rider","05. The Cars - Just What I Needed","06. Rickie Lee Jones - Chuck E.\u0027s in Love","07. Blue Swede - Hooked on a Feeling","08. Jackson Browne - Running on Empty","09. Chicago - If You Leave Me Now","10. Joni Mitchell - Big Yellow Taxi","11. Bread - Guitar Man","12. Rod Stewart - Da Ya Think I\u2019m Sexy","13. Lauren Wood - Hollywood","14. Wizzard - See My Baby Jive","15. Bette Midler - The Rose","16. Maxine Nightingale - Right Back Where We Started From","17. Frankie Valli - Grease (2006 Remaster)","18. KC And The Sunshine Band - That\u2019s the Way (I Like It)","19. Tina Turner - Sometimes When We Touch","20. Chaka Khan - I\u2019m Every Woman","21. Orleans - Still the One","22. Ramones - Blitzkrieg Bop","23. The Doobie Brothers - Black Water","24. Gerry Rafferty - Right down the Line","25. James Taylor - You\u2019ve Got a Friend","26. Foreigner - Cold as Ice (2006 Remaster)","27. Cliff Richard - We Don\u0027t Talk Anymore","28. Roberta Flack - Killing Me Softly with His Song","29. Van Morrison - Crazy Love","30. Stephen Stills - Love the One You\u2019re With","31. Candi Staton - Young Hearts Run Free","32. Chris Rea - Fool (If You Think It\u2019s Over)","33. Dionne Warwick - Then Came You","34. The Trammps - Disco Inferno","35. Nicolette Larson - Lotta Love","36. Todd Rundgren - I Saw the Light (2006 Remaster)","37. The Doors - Riders on the Storm (2017 Remaster)","38. Randy Vanwarmer - Just When I Needed You Most","39. America - A Horse with No Name","40. Daryl Hall \u0026 John Oates - She\u0027s Gone","41. Bloodstone - Natural High","42. Gordon Lightfoot - Sundown","43. Crosby, Stills \u0026 Nash - Just a Song Before I Go","44. Sister Sledge - We Are Family","45. George McCrae - Rock Your Baby","46. Gary Wright - Dream Weaver","47. Eddie Rabbitt - Every Which Way but Loose","48. Olivia Newton-John - Have You Never Been Mellow","49. Aretha Franklin - Day Dreaming","50. Pil\u00F6t - Magic","51. Linda Ronstadt - Desperado","52. Talking Heads - Psycho Killer (2005 Remaster)","53. England Dan \u0026 John Ford Coley - I\u2019d Really Love to See You Tonight","54. Jefferson Starship - Jane","55. The Pretenders - Brass in Pocket (2006 Remaster)","56. Firefall - You Are the Woman","57. Carole Bayer Sager - You\u0027re Moving Out Today","58. Warren Zevon - Werewolves of London (2007 Remaster)","59. Carly Simon - You\u0027re So Vain (2023 Remaster)","60. Bad Company - Feel like Makin\u2019 Love (2015 Remaster)","61. George Benson - Breezin\u2019","62. Alice Cooper - School\u2019s Out","63. Hot Chocolate - You Sexy Thing (2011 Remaster)","64. Chic - Good Times","65. Brook Benton - Rainy Night in Georgia","66. Randy Crawford - Street Life","67. Faces - Ooh La La","68. Andrew Gold - Lonely Boy","69. Curtis Mayfield - Move On Up","70. Donny Hathaway - Jealous Guy"],"checked":[[0,0,0,0,0,0,0,0,0,0,0,0,0,0,0,0,0,0,0,0,0,0,0,0,0,0,0,0,0,0,0,0,0,0,0,0,0,0,0,0,0,0,0,0,0,0,0,0,0,0,0,0,0,0,0,0,0,0,0,0,0,0,0,0,0,0,0,0,0,0],[0,0,0,0,0,0,0,0,0,0,0,0,0,0,0,0,0,0,0,0,0,0,0,0,0,0,0,0,0,0,0,0,0,0,0,0,0,0,0,0,0,0,0,0,0,0,0,0,0,0,0,0,0,0,0,0,0,0,0,0,0,0,0,0,0,0,0,0,0,0],[0,0,0,0,0,0,0,0,0,0,0,0,0,0,0,0,0,0,0,0,0,0,0,0,0,0,0,0,0,0,0,0,0,0,0,0,0,0,0,0,0,0,0,0,0,0,0,0,0,0,0,0,0,0,0,0,0,0,0,0,0,0,0,0,0,0,0,0,0,0],[0,0,0,0,0,0,0,0,0,0,0,0,0,0,0,0,0,0,0,0,0,0,0,0,0,0,0,0,0,0,0,0,0,0,0,0,0,0,0,0,0,0,0,0,0,0,0,0,0,0,0,0,0,0,0,0,0,0,0,0,0,0,0,0,0,0,0,0,0,0],[0,0,0,0,0,0,0,0,0,0,0,0,0,0,0,0,0,0,0,0,0,0,0,0,0,0,0,0,0,0,0,0,0,0,0,0,0,0,0,0,0,0,0,0,0,0,0,0,0,0,0,0,0,0,0,0,0,0,0,0,0,0,0,0,0,0,0,0,0,0]]},{"name":"1980s","songs":["01. Fleetwood Mac - Everywhere (2018 Remaster)","02. Madonna - La Isla Bonita","03. Christopher Cross - Arthur\u0027s Theme (Best That You Can Do)","04. Kate Bush - Babooshka","05. Diana Ross - Chain Reaction","06. Carole King - Crying in the Rain","07. Ambrosia - Biggest Part of Me","08. Roxette - The Look","09. Tina Turner - What\u0027s Love Got to Do with It","10. Pet Shop Boys - Always on My Mind","11. Starship - We Built This City","12. A-Ha - Take On Me","13. Alannah Myles - Black Velvet","14. Bette Midler - Wind Beneath My Wings","15. Climie Fisher - Love Changes (Everything)","16. Duran Duran - Notorious","17. Limahl - Never Ending Story","18. Chaka Khan - I Feel for You","19. Chris Rea - Josephine","20. Stevie Nicks - Edge of Seventeen (2016 Remaster)","21. Spandau Ballet - Gold","22. Chicago - You\u0027re the Inspiration","23. Faith No More - Epic (Radio Edit)","24. Narada Michael Walden - Gimme Gimme Gimme (feat. Patti Austin)","25. Foreigner - I Want to Know What Love Is (1999 Remaster)","26. George Benson - Give Me the Night","27. Peter Cetera - Glory of Love","28. Joey Scarbury - Believe It or Not (From Greatest American Hero)","29. John Parr - St. Elmo\u0027s Fire (Man in Motion)","30. Joy Division - Love Will Tear Us Apart","31. Kajagoogoo - Too Shy (2004 Remaster)","32. Laura Branigan - Self Control","33. London Boys - London Nights","34. Marillion - Kayleigh (2017 Remaster)","35. Robert Palmer - Simply Irresistible","36. Rod Stewart - Young Turks","37. Talk Talk - It\u0027s My Life","38. Tanita Tikaram - Twist in My Sobriety","39. The Cars - Drive","40. Michael McDonald - I Keep Forgettin (Every Time You\u0027re Near)","41. Yes - Owner of a Lonely Heart","42. New Order - Blue Monday \u002788 (2015 Remaster)","43. Nu Shooz - I Can\u2019t Wait","44. Peter Schilling - Major Tom (Coming Home)","45. The Pretenders - Don\u0027t Get Me Wrong","46. The Dream Academy - Life in a Northern Town","47. Simply Red - Holding Back the Years","48. Starpoint - Object of My Desire","49. Talking Heads - This Must Be the Place (Naive Melody) [2005 Remaster]","50. The Beach Boys - Kokomo","51. The Proclaimers - I\u0027m Gonna Be (500 Miles)","52. The Smiths - This Charming Man (2011 Remaster)","53. Sister Sledge - Frankie","54. Twisted Sister - We\u2019re Not Gonna Take It","55. Whitesnake - Is This Love"],"checked":[[0,0,0,0,0,0,0,0,0,0,0,0,0,0,0,0,0,0,0,0,0,0,0,0,0,0,0,0,0,0,0,0,0,0,0,0,0,0,0,0,0,0,0,0,0,0,0,0,0,0,0,0,0,0,0],[0,0,0,0,0,0,0,0,0,0,0,0,0,0,0,0,0,0,0,0,0,0,0,0,0,0,0,0,0,0,0,0,0,0,0,0,0,0,0,0,0,0,0,0,0,0,0,0,0,0,0,0,0,0,0],[0,0,0,0,0,0,0,0,0,0,0,0,0,0,0,0,0,0,0,0,0,0,0,0,0,0,0,0,0,0,0,0,0,0,0,0,0,0,0,0,0,0,0,0,0,0,0,0,0,0,0,0,0,0,0],[0,0,0,0,0,0,0,0,0,0,0,0,0,0,0,0,0,0,0,0,0,0,0,0,0,0,0,0,0,0,0,0,0,0,0,0,0,0,0,0,0,0,0,0,0,0,0,0,0,0,0,0,0,0,0],[0,0,0,0,0,0,0,0,0,0,0,0,0,0,0,0,0,0,0,0,0,0,0,0,0,0,0,0,0,0,0,0,0,0,0,0,0,0,0,0,0,0,0,0,0,0,0,0,0,0,0,0,0,0,0]]},{"name":"1990s","songs":["01. Roxette - Joyride","02. Tina Turner - Missing You","03. Nada Surf - Popular","04. Madonna - Vogue","05. Spacehog - In the Meantime","06. Blur - Girls and Boys","07. Seal - Crazy","08. Shola Ama - You Might Need Somebody","09. Rod Stewart - Rhythm of My Heart","10. Cher - Walking in Memphis","11. Red Hot Chili Peppers - Under the Bridge","12. Faith Hill - This Kiss","13. Alanis Morissette - Thank U (Remix)","14. Simply Red - Something Got Me Started","15. Roxette - Fading Like a Flower (Every Time You Leave)","16. The Corrs - So Young","17. Tasmin Archer - Sleeping Satellite","18. Lene Marlin - Sitting Down Here","19. The Jesus And Mary Chain - Sometimes Always","20. Robin S - Show Me Love","21. Third Eye Blind - Semi-charmed Life","22. Mark Morrison - Return of the Mack (C \u0026 J Street Mix)","23. Babylon Zoo - Spaceman (Radio Edit)","24. Madonna - Ray of Light (Radio Edit)","25. Shampoo     - Trouble","26. Tori Amos - Professional Widow (Armand\u0027s Star Trunk Funk Mix)","27. 98\u00BA - Only Wanna Be with You","28. Barenaked Ladies - One Week","29. Grace - Not Over Yet","30. Jennifer Love Hewitt - No Ordinary Love","31. All Saints - Never Ever (Radio Edit)","32. Peter Andre - Mysterious Girl (Radio Edit)","33. En Vogue - My Lovin\u2019 (You\u2019re Never Gonna Get It)","34. Fleetwood Mac - Hollywood (Some Other Kind of Town)","35. Catatonia - Mulder and Scully","36. Faith Evans - Love like This","37. Seal - Kiss from a Rose","38. Gina G - Just a Little Bit (Radio Edit)","39. Alanis Morissette - Ironic (2015 Remaster)","40. Morrissey - The Last of the Famous International Playboys","41. Diddy - I\u2019ll Be Missing You (feat. Faith Evans \u0026 112)","42. Eternal - I Wanna Be the Only One (feat. BeBe Winans)","43. All-4-One - I Swear","44. Robert Palmer - Mercy Mercy Me  I Want You","45. All Saints - Lady Marmalade (\u201998 Remix)","46. Donna Lewis - I Love You Always Forever","47. The Notorious B.I.G. - Hypnotize (2014 Remaster)","48. Rod Stewart - Have I Told You Lately","49. Deee-Lite - Groove Is in the Heart","50. Pet Shop Boys - Go West (2003 Remaster)","51. Adina Howard - Freak Like Me","52. Simply Red - Fairground","53. En Vogue - Don\u2019t Let Go (Love)","54. The Corrs - Breathless","55. They Might Be Giants - Birdhouse in Your Soul","56. Cher - Believe","57. Blur - Beetlebum (2012 Remaster)","58. Geri Halliwell - Bag It Up","59. Big Mountain - Baby, I Love Your Way","60. Jimmy Nail - Ain\u2019t No Doubt"],"checked":[[0,0,0,0,0,0,0,0,0,0,0,0,0,0,0,0,0,0,0,0,0,0,0,0,0,0,0,0,0,0,0,0,0,0,0,0,0,0,0,0,0,0,0,0,0,0,0,0,0,0,0,0,0,0,0,0,0,0,0,0],[0,0,0,0,0,0,0,0,0,0,0,0,0,0,0,0,0,0,0,0,0,0,0,0,0,0,0,0,0,0,0,0,0,0,0,0,0,0,0,0,0,0,0,0,0,0,0,0,0,0,0,0,0,0,0,0,0,0,0,0],[0,0,0,0,0,0,0,0,0,0,0,0,0,0,0,0,0,0,0,0,0,0,0,0,0,0,0,0,0,0,0,0,0,0,0,0,0,0,0,0,0,0,0,0,0,0,0,0,0,0,0,0,0,0,0,0,0,0,0,0],[0,0,0,0,0,0,0,0,0,0,0,0,0,0,0,0,0,0,0,0,0,0,0,0,0,0,0,0,0,0,0,0,0,0,0,0,0,0,0,0,0,0,0,0,0,0,0,0,0,0,0,0,0,0,0,0,0,0,0,0],[0,0,0,0,0,0,0,0,0,0,0,0,0,0,0,0,0,0,0,0,0,0,0,0,0,0,0,0,0,0,0,0,0,0,0,0,0,0,0,0,0,0,0,0,0,0,0,0,0,0,0,0,0,0,0,0,0,0,0,0]]},{"name":"2000s","songs":["01. David Guetta - Memories (feat. Kid Cudi)","02. Nickelback - How You Remind Me","03. Kevin Lyttle - Turn Me On","04. Madonna - Hung Up (Radio Version)","05. Roxette - The Centre of the Heart","06. Jay Z - Numb  Encore","07. Rupee - Tempted to Touch","08. Jason DeRulo - Whatcha Say","09. Michael Bubl\u00E9 - Sway","10. Kate Ryan - D\u00E9senchant\u00E9e","11. Panic! At The Disco - I Write Sins Not Tragedies","12. Gorillaz - Feel Good Inc","13. Green Day - American Idiot","14. Missy Elliott - Work It","15. Red Hot Chili Peppers - Can\u2019t Stop","16. Flo Rida - Low (feat. T-Pain)","17. Paramore - All I Wanted","18. B.O.B - Nothin\u2019 on You (feat. Bruno Mars)","19. All Saints - Pure Shores","20. Iyaz - Replay (feat. Flo Rida)","21. Gym Class Heroes - Cupid\u2019s Chokehold  Breakfast in America","22. Daniel Powter - Bad Day","23. Kid Rock - All Summer Long","24. Matchbox Twenty - Unwell","25. Faith Hill - There You\u2019ll Be","26. Cassie - Me \u0026 U","27. P.O.D. - Youth of the Nation","28. Alanis Morissette - Hands Clean","29. Paris Hilton - Stars Are Blind","30. My Chemical Romance - Teenagers","31. Ryan Cabrera - True","32. Simple Plan - I\u2019m Just a Kid","33. Lupe Fiasco - Superstar (feat. Matthew Santos)","34. Michelle Branch - Everywhere","35. Tamia - Officially Missing You","36. 3Oh!3 - STARSTRUKK (feat. Katy Perry)","37. Blur - Out of Time","38. Sean Paul - Temperature","39. Hard-Fi - Hard to Beat","40. Faith Evans - I Love You","41. Dante Thomas - Miss California","42. Pretty Ricky - Grind with Me","43. A Rocket To The Moon - Like We Used To","44. Jaheim - Put That Woman First","45. Cobra Starship - Good Girls Go Bad","46. Twista - Overnight Celebrity","47. Regina Spektor - Two Birds","48. Shinedown - Second Chance","49. The Wombats - Let\u2019s Dance to Joy Division","50. Lil\u0027 Kim - Magic Stick","51. LCD Soundsystem - Daft Punk Is Playing at My House (Radio Edit)","52. Fabolous - Into You","53. The Veronicas - Untouched","54. Musiq Soulchild - sobeautiful","55. New Order - Crystal (Radio Edit)","56. Danity Kane - Damaged","57. Mario Winans - I Don\u0027t Wanna Know (feat. Enya \u0026 Diddy)","58. Lily Allen - LDN","59. Paolo Nutini - Candy","60. Coldplay - Viva La Vida","61. Wiley - Wearing My Rolex (Radio Edit)","62. Jason Mraz - I\u2019m Yours","63. Death Cab For Cutie - I Will Follow You into the Dark","64. James Blunt - You\u2019re Beautiful","65. The Darkness - I Believe in a Thing Called Love","66. Brandy - What About Us","67. 112 - Peaches and Cream","68. Linkin Park - In the End","69. The Corrs - Breathless","70. Uncle Kracker - Follow Me"],"checked":[[0,0,0,0,0,0,0,0,0,0,0,0,0,0,0,0,0,0,0,0,0,0,0,0,0,0,0,0,0,0,0,0,0,0,0,0,0,0,0,0,0,0,0,0,0,0,0,0,0,0,0,0,0,0,0,0,0,0,0,0,0,0,0,0,0,0,0,0,0,0],[0,0,0,0,0,0,0,0,0,0,0,0,0,0,0,0,0,0,0,0,0,0,0,0,0,0,0,0,0,0,0,0,0,0,0,0,0,0,0,0,0,0,0,0,0,0,0,0,0,0,0,0,0,0,0,0,0,0,0,0,0,0,0,0,0,0,0,0,0,0],[0,0,0,0,0,0,0,0,0,0,0,0,0,0,0,0,0,0,0,0,0,0,0,0,0,0,0,0,0,0,0,0,0,0,0,0,0,0,0,0,0,0,0,0,0,0,0,0,0,0,0,0,0,0,0,0,0,0,0,0,0,0,0,0,0,0,0,0,0,0],[0,0,0,0,0,0,0,0,0,0,0,0,0,0,0,0,0,0,0,0,0,0,0,0,0,0,0,0,0,0,0,0,0,0,0,0,0,0,0,0,0,0,0,0,0,0,0,0,0,0,0,0,0,0,0,0,0,0,0,0,0,0,0,0,0,0,0,0,0,0],[0,0,0,0,0,0,0,0,0,0,0,0,0,0,0,0,0,0,0,0,0,0,0,0,0,0,0,0,0,0,0,0,0,0,0,0,0,0,0,0,0,0,0,0,0,0,0,0,0,0,0,0,0,0,0,0,0,0,0,0,0,0,0,0,0,0,0,0,0,0]]}]